labirint_parser
