Metadata-Version: 2.1
Name: labirint-parse
Version: 0.1
Summary: Allows you to find out if a particular book is in stock and its price.
Home-page: UNKNOWN
Author-email: aleks.zhuravlev2002@mail.ru
License: UNKNOWN
Platform: UNKNOWN
